<?xml version="1.0" encoding="UTF-8" ?>
<!DOCTYPE mapper PUBLIC "-//mybatis.org//DTD Mapper 3.0//EN" "http://mybatis.org/dtd/mybatis-3-mapper.dtd" >
<mapper namespace="cn.edu.hist.mapper.YppmbackupMapper" >
  <resultMap id="BaseResultMap" type="cn.edu.hist.model.Yppmbackup" >
    <!--
      WARNING - @mbggenerated
      This element is automatically generated by MyBatis Generator, do not modify.
    -->
    <id column="ID" property="id" jdbcType="VARCHAR" />
    <result column="BM" property="bm" jdbcType="VARCHAR" />
    <result column="MC" property="mc" jdbcType="VARCHAR" />
    <result column="JX" property="jx" jdbcType="VARCHAR" />
    <result column="DW" property="dw" jdbcType="VARCHAR" />
    <result column="ZHXS" property="zhxs" jdbcType="VARCHAR" />
    <result column="LB" property="lb" jdbcType="VARCHAR" />
    <result column="ZT" property="zt" jdbcType="CHAR" />
    <result column="ZL" property="zl" jdbcType="VARCHAR" />
    <result column="HL" property="hl" jdbcType="VARCHAR" />
    <result column="YB" property="yb" jdbcType="CHAR" />
    <result column="YBBM" property="ybbm" jdbcType="VARCHAR" />
    <result column="BZ" property="bz" jdbcType="VARCHAR" />
    <result column="VCHAR1" property="vchar1" jdbcType="VARCHAR" />
    <result column="VCHAR2" property="vchar2" jdbcType="VARCHAR" />
    <result column="VCHAR3" property="vchar3" jdbcType="VARCHAR" />
    <result column="GG" property="gg" jdbcType="VARCHAR" />
  </resultMap>
  <sql id="Example_Where_Clause" >
    <!--
      WARNING - @mbggenerated
      This element is automatically generated by MyBatis Generator, do not modify.
    -->
    <where >
      <foreach collection="oredCriteria" item="criteria" separator="or" >
        <if test="criteria.valid" >
          <trim prefix="(" suffix=")" prefixOverrides="and" >
            <foreach collection="criteria.criteria" item="criterion" >
              <choose >
                <when test="criterion.noValue" >
                  and ${criterion.condition}
                </when>
                <when test="criterion.singleValue" >
                  and ${criterion.condition} #{criterion.value}
                </when>
                <when test="criterion.betweenValue" >
                  and ${criterion.condition} #{criterion.value} and #{criterion.secondValue}
                </when>
                <when test="criterion.listValue" >
                  and ${criterion.condition}
                  <foreach collection="criterion.value" item="listItem" open="(" close=")" separator="," >
                    #{listItem}
                  </foreach>
                </when>
              </choose>
            </foreach>
          </trim>
        </if>
      </foreach>
    </where>
  </sql>
  <sql id="Update_By_Example_Where_Clause" >
    <!--
      WARNING - @mbggenerated
      This element is automatically generated by MyBatis Generator, do not modify.
    -->
    <where >
      <foreach collection="example.oredCriteria" item="criteria" separator="or" >
        <if test="criteria.valid" >
          <trim prefix="(" suffix=")" prefixOverrides="and" >
            <foreach collection="criteria.criteria" item="criterion" >
              <choose >
                <when test="criterion.noValue" >
                  and ${criterion.condition}
                </when>
                <when test="criterion.singleValue" >
                  and ${criterion.condition} #{criterion.value}
                </when>
                <when test="criterion.betweenValue" >
                  and ${criterion.condition} #{criterion.value} and #{criterion.secondValue}
                </when>
                <when test="criterion.listValue" >
                  and ${criterion.condition}
                  <foreach collection="criterion.value" item="listItem" open="(" close=")" separator="," >
                    #{listItem}
                  </foreach>
                </when>
              </choose>
            </foreach>
          </trim>
        </if>
      </foreach>
    </where>
  </sql>
  <sql id="Base_Column_List" >
    <!--
      WARNING - @mbggenerated
      This element is automatically generated by MyBatis Generator, do not modify.
    -->
    ID, BM, MC, JX, DW, ZHXS, LB, ZT, ZL, HL, YB, YBBM, BZ, VCHAR1, VCHAR2, VCHAR3, GG
  </sql>
  <select id="selectByExample" resultMap="BaseResultMap" parameterType="cn.edu.hist.model.YppmbackupExample" >
    <!--
      WARNING - @mbggenerated
      This element is automatically generated by MyBatis Generator, do not modify.
    -->
    select
    <if test="distinct" >
      distinct
    </if>
    'true' as QUERYID,
    <include refid="Base_Column_List" />
    from yppmbackup
    <if test="_parameter != null" >
      <include refid="Example_Where_Clause" />
    </if>
    <if test="orderByClause != null" >
      order by ${orderByClause}
    </if>
  </select>
  <select id="selectByPrimaryKey" resultMap="BaseResultMap" parameterType="java.lang.String" >
    <!--
      WARNING - @mbggenerated
      This element is automatically generated by MyBatis Generator, do not modify.
    -->
    select 
    <include refid="Base_Column_List" />
    from yppmbackup
    where ID = #{id,jdbcType=VARCHAR}
  </select>
  <delete id="deleteByPrimaryKey" parameterType="java.lang.String" >
    <!--
      WARNING - @mbggenerated
      This element is automatically generated by MyBatis Generator, do not modify.
    -->
    delete from yppmbackup
    where ID = #{id,jdbcType=VARCHAR}
  </delete>
  <delete id="deleteByExample" parameterType="cn.edu.hist.model.YppmbackupExample" >
    <!--
      WARNING - @mbggenerated
      This element is automatically generated by MyBatis Generator, do not modify.
    -->
    delete from yppmbackup
    <if test="_parameter != null" >
      <include refid="Example_Where_Clause" />
    </if>
  </delete>
  <insert id="insert" parameterType="cn.edu.hist.model.Yppmbackup" >
    <!--
      WARNING - @mbggenerated
      This element is automatically generated by MyBatis Generator, do not modify.
    -->
    insert into yppmbackup (ID, BM, MC, JX, 
      DW, ZHXS, LB, ZT, 
      ZL, HL, YB, YBBM, 
      BZ, VCHAR1, VCHAR2, 
      VCHAR3, GG)
    values (#{id,jdbcType=VARCHAR}, #{bm,jdbcType=VARCHAR}, #{mc,jdbcType=VARCHAR}, #{jx,jdbcType=VARCHAR}, 
      #{dw,jdbcType=VARCHAR}, #{zhxs,jdbcType=VARCHAR}, #{lb,jdbcType=VARCHAR}, #{zt,jdbcType=CHAR}, 
      #{zl,jdbcType=VARCHAR}, #{hl,jdbcType=VARCHAR}, #{yb,jdbcType=CHAR}, #{ybbm,jdbcType=VARCHAR}, 
      #{bz,jdbcType=VARCHAR}, #{vchar1,jdbcType=VARCHAR}, #{vchar2,jdbcType=VARCHAR}, 
      #{vchar3,jdbcType=VARCHAR}, #{gg,jdbcType=VARCHAR})
  </insert>
  <insert id="insertSelective" parameterType="cn.edu.hist.model.Yppmbackup" >
    <!--
      WARNING - @mbggenerated
      This element is automatically generated by MyBatis Generator, do not modify.
    -->
    insert into yppmbackup
    <trim prefix="(" suffix=")" suffixOverrides="," >
      <if test="id != null" >
        ID,
      </if>
      <if test="bm != null" >
        BM,
      </if>
      <if test="mc != null" >
        MC,
      </if>
      <if test="jx != null" >
        JX,
      </if>
      <if test="dw != null" >
        DW,
      </if>
      <if test="zhxs != null" >
        ZHXS,
      </if>
      <if test="lb != null" >
        LB,
      </if>
      <if test="zt != null" >
        ZT,
      </if>
      <if test="zl != null" >
        ZL,
      </if>
      <if test="hl != null" >
        HL,
      </if>
      <if test="yb != null" >
        YB,
      </if>
      <if test="ybbm != null" >
        YBBM,
      </if>
      <if test="bz != null" >
        BZ,
      </if>
      <if test="vchar1 != null" >
        VCHAR1,
      </if>
      <if test="vchar2 != null" >
        VCHAR2,
      </if>
      <if test="vchar3 != null" >
        VCHAR3,
      </if>
      <if test="gg != null" >
        GG,
      </if>
    </trim>
    <trim prefix="values (" suffix=")" suffixOverrides="," >
      <if test="id != null" >
        #{id,jdbcType=VARCHAR},
      </if>
      <if test="bm != null" >
        #{bm,jdbcType=VARCHAR},
      </if>
      <if test="mc != null" >
        #{mc,jdbcType=VARCHAR},
      </if>
      <if test="jx != null" >
        #{jx,jdbcType=VARCHAR},
      </if>
      <if test="dw != null" >
        #{dw,jdbcType=VARCHAR},
      </if>
      <if test="zhxs != null" >
        #{zhxs,jdbcType=VARCHAR},
      </if>
      <if test="lb != null" >
        #{lb,jdbcType=VARCHAR},
      </if>
      <if test="zt != null" >
        #{zt,jdbcType=CHAR},
      </if>
      <if test="zl != null" >
        #{zl,jdbcType=VARCHAR},
      </if>
      <if test="hl != null" >
        #{hl,jdbcType=VARCHAR},
      </if>
      <if test="yb != null" >
        #{yb,jdbcType=CHAR},
      </if>
      <if test="ybbm != null" >
        #{ybbm,jdbcType=VARCHAR},
      </if>
      <if test="bz != null" >
        #{bz,jdbcType=VARCHAR},
      </if>
      <if test="vchar1 != null" >
        #{vchar1,jdbcType=VARCHAR},
      </if>
      <if test="vchar2 != null" >
        #{vchar2,jdbcType=VARCHAR},
      </if>
      <if test="vchar3 != null" >
        #{vchar3,jdbcType=VARCHAR},
      </if>
      <if test="gg != null" >
        #{gg,jdbcType=VARCHAR},
      </if>
    </trim>
  </insert>
  <select id="countByExample" parameterType="cn.edu.hist.model.YppmbackupExample" resultType="java.lang.Integer" >
    <!--
      WARNING - @mbggenerated
      This element is automatically generated by MyBatis Generator, do not modify.
    -->
    select count(*) from yppmbackup
    <if test="_parameter != null" >
      <include refid="Example_Where_Clause" />
    </if>
  </select>
  <update id="updateByExampleSelective" parameterType="map" >
    <!--
      WARNING - @mbggenerated
      This element is automatically generated by MyBatis Generator, do not modify.
    -->
    update yppmbackup
    <set >
      <if test="record.id != null" >
        ID = #{record.id,jdbcType=VARCHAR},
      </if>
      <if test="record.bm != null" >
        BM = #{record.bm,jdbcType=VARCHAR},
      </if>
      <if test="record.mc != null" >
        MC = #{record.mc,jdbcType=VARCHAR},
      </if>
      <if test="record.jx != null" >
        JX = #{record.jx,jdbcType=VARCHAR},
      </if>
      <if test="record.dw != null" >
        DW = #{record.dw,jdbcType=VARCHAR},
      </if>
      <if test="record.zhxs != null" >
        ZHXS = #{record.zhxs,jdbcType=VARCHAR},
      </if>
      <if test="record.lb != null" >
        LB = #{record.lb,jdbcType=VARCHAR},
      </if>
      <if test="record.zt != null" >
        ZT = #{record.zt,jdbcType=CHAR},
      </if>
      <if test="record.zl != null" >
        ZL = #{record.zl,jdbcType=VARCHAR},
      </if>
      <if test="record.hl != null" >
        HL = #{record.hl,jdbcType=VARCHAR},
      </if>
      <if test="record.yb != null" >
        YB = #{record.yb,jdbcType=CHAR},
      </if>
      <if test="record.ybbm != null" >
        YBBM = #{record.ybbm,jdbcType=VARCHAR},
      </if>
      <if test="record.bz != null" >
        BZ = #{record.bz,jdbcType=VARCHAR},
      </if>
      <if test="record.vchar1 != null" >
        VCHAR1 = #{record.vchar1,jdbcType=VARCHAR},
      </if>
      <if test="record.vchar2 != null" >
        VCHAR2 = #{record.vchar2,jdbcType=VARCHAR},
      </if>
      <if test="record.vchar3 != null" >
        VCHAR3 = #{record.vchar3,jdbcType=VARCHAR},
      </if>
      <if test="record.gg != null" >
        GG = #{record.gg,jdbcType=VARCHAR},
      </if>
    </set>
    <if test="_parameter != null" >
      <include refid="Update_By_Example_Where_Clause" />
    </if>
  </update>
  <update id="updateByExample" parameterType="map" >
    <!--
      WARNING - @mbggenerated
      This element is automatically generated by MyBatis Generator, do not modify.
    -->
    update yppmbackup
    set ID = #{record.id,jdbcType=VARCHAR},
      BM = #{record.bm,jdbcType=VARCHAR},
      MC = #{record.mc,jdbcType=VARCHAR},
      JX = #{record.jx,jdbcType=VARCHAR},
      DW = #{record.dw,jdbcType=VARCHAR},
      ZHXS = #{record.zhxs,jdbcType=VARCHAR},
      LB = #{record.lb,jdbcType=VARCHAR},
      ZT = #{record.zt,jdbcType=CHAR},
      ZL = #{record.zl,jdbcType=VARCHAR},
      HL = #{record.hl,jdbcType=VARCHAR},
      YB = #{record.yb,jdbcType=CHAR},
      YBBM = #{record.ybbm,jdbcType=VARCHAR},
      BZ = #{record.bz,jdbcType=VARCHAR},
      VCHAR1 = #{record.vchar1,jdbcType=VARCHAR},
      VCHAR2 = #{record.vchar2,jdbcType=VARCHAR},
      VCHAR3 = #{record.vchar3,jdbcType=VARCHAR},
      GG = #{record.gg,jdbcType=VARCHAR}
    <if test="_parameter != null" >
      <include refid="Update_By_Example_Where_Clause" />
    </if>
  </update>
  <update id="updateByPrimaryKeySelective" parameterType="cn.edu.hist.model.Yppmbackup" >
    <!--
      WARNING - @mbggenerated
      This element is automatically generated by MyBatis Generator, do not modify.
    -->
    update yppmbackup
    <set >
      <if test="bm != null" >
        BM = #{bm,jdbcType=VARCHAR},
      </if>
      <if test="mc != null" >
        MC = #{mc,jdbcType=VARCHAR},
      </if>
      <if test="jx != null" >
        JX = #{jx,jdbcType=VARCHAR},
      </if>
      <if test="dw != null" >
        DW = #{dw,jdbcType=VARCHAR},
      </if>
      <if test="zhxs != null" >
        ZHXS = #{zhxs,jdbcType=VARCHAR},
      </if>
      <if test="lb != null" >
        LB = #{lb,jdbcType=VARCHAR},
      </if>
      <if test="zt != null" >
        ZT = #{zt,jdbcType=CHAR},
      </if>
      <if test="zl != null" >
        ZL = #{zl,jdbcType=VARCHAR},
      </if>
      <if test="hl != null" >
        HL = #{hl,jdbcType=VARCHAR},
      </if>
      <if test="yb != null" >
        YB = #{yb,jdbcType=CHAR},
      </if>
      <if test="ybbm != null" >
        YBBM = #{ybbm,jdbcType=VARCHAR},
      </if>
      <if test="bz != null" >
        BZ = #{bz,jdbcType=VARCHAR},
      </if>
      <if test="vchar1 != null" >
        VCHAR1 = #{vchar1,jdbcType=VARCHAR},
      </if>
      <if test="vchar2 != null" >
        VCHAR2 = #{vchar2,jdbcType=VARCHAR},
      </if>
      <if test="vchar3 != null" >
        VCHAR3 = #{vchar3,jdbcType=VARCHAR},
      </if>
      <if test="gg != null" >
        GG = #{gg,jdbcType=VARCHAR},
      </if>
    </set>
    where ID = #{id,jdbcType=VARCHAR}
  </update>
  <update id="updateByPrimaryKey" parameterType="cn.edu.hist.model.Yppmbackup" >
    <!--
      WARNING - @mbggenerated
      This element is automatically generated by MyBatis Generator, do not modify.
    -->
    update yppmbackup
    set BM = #{bm,jdbcType=VARCHAR},
      MC = #{mc,jdbcType=VARCHAR},
      JX = #{jx,jdbcType=VARCHAR},
      DW = #{dw,jdbcType=VARCHAR},
      ZHXS = #{zhxs,jdbcType=VARCHAR},
      LB = #{lb,jdbcType=VARCHAR},
      ZT = #{zt,jdbcType=CHAR},
      ZL = #{zl,jdbcType=VARCHAR},
      HL = #{hl,jdbcType=VARCHAR},
      YB = #{yb,jdbcType=CHAR},
      YBBM = #{ybbm,jdbcType=VARCHAR},
      BZ = #{bz,jdbcType=VARCHAR},
      VCHAR1 = #{vchar1,jdbcType=VARCHAR},
      VCHAR2 = #{vchar2,jdbcType=VARCHAR},
      VCHAR3 = #{vchar3,jdbcType=VARCHAR},
      GG = #{gg,jdbcType=VARCHAR}
    where ID = #{id,jdbcType=VARCHAR}
  </update>
</mapper>